Workbook

Sheet Intrari
A1: LUMIS: calculator de profit pe produs
A2: Celulele galbene sunt de completat. Gol = necunoscut (nu zero). Nicio valoare nu e inventată; nu sunt prețuri recomandate.
A4: Intrare | B4: Unitate | C4: Valoare | D4: Notă
A5: Preț filament | B5: lei / kg | D5: Din factura ta, fără TVA dacă ești plătitor de TVA. Singurul preț găsit în cercetare e în euro, de la un magazin din Letonia: nu se aplică.
A6: Cost mașină | B6: lei / oră | D6: Amortizare imprimantă + energie + întreținere, împreună. Nu le mai număra separat.
A7: Manoperă proprie | B7: lei / oră | D7: Cât valorează o oră din timpul tău. 0 e o valoare reală: pune-o doar dacă chiar nu o contabilizezi.
A8: Comision platformă | B8: % din preț | D8: De pe marketplace sau procesator de plăți. Se verifică în tariful actual.
A9: Contribuție transport | B9: lei / comandă | D9: Cât din transport plătești tu, nu clientul.
A10: Rată de rebuturi | B10: % din bucăți | D10: Din printuri reale. Fără print, lasă gol.

Sheet Produse
A1: Produs | B1: Ore de print (măsurat) | C1: Grame filament (măsurat) | D1: Componente (lei) | E1: Minute manoperă / bucată | F1: Preț de vânzare, fără TVA (lei) - îl alege proprietarul | G1: Reper de preț (nu e preț RO) | H1: Cost material (lei) | I1: Cost mașină (lei) | J1: Cost manoperă (lei) | K1: Cost rebuturi (lei) | L1: Cost total (lei) | M1: Venit net după comision (lei) | N1: Profit / bucată (lei) | O1: Profit / oră de imprimantă (lei) | P1: Marjă brută (% din venit net)
A2: Lampă LUMIS, abajur Wave + soclu | G2: Fără sursă | H2: =IF(OR(C2="",Intrari!$C$5=""),"",C2/1000*Intrari!$C$5) | I2: =IF(OR(B2="",Intrari!$C$6=""),"",B2*Intrari!$C$6) | J2: =IF(OR(E2="",Intrari!$C$7=""),"",E2/60*Intrari!$C$7) | K2: =IF(OR(H2="",I2="",Intrari!$C$10=""),"",(H2+I2)*Intrari!$C$10/100) | L2: =IF(OR(H2="",I2="",J2="",K2="",D2=""),"",H2+I2+J2+K2+D2) | M2: =IF(OR(F2="",Intrari!$C$8=""),"",F2*(1-Intrari!$C$8/100)-IF(Intrari!$C$9="",0,Intrari!$C$9)) | N2: =IF(OR(L2="",M2=""),"",M2-L2) | O2: =IF(OR(N2="",B2="",B2=0),"",N2/B2) | P2: =IF(OR(N2="",M2="",M2=0),"",N2/M2)
A3: Lampă LUMIS, Litofanie | G3: Abajur litofanie, magazin internațional: 65 USD (o sursă, fără transport/taxe) | H3: =IF(OR(C3="",Intrari!$C$5=""),"",C3/1000*Intrari!$C$5) | I3: =IF(OR(B3="",Intrari!$C$6=""),"",B3*Intrari!$C$6) | J3: =IF(OR(E3="",Intrari!$C$7=""),"",E3/60*Intrari!$C$7) | K3: =IF(OR(H3="",I3="",Intrari!$C$10=""),"",(H3+I3)*Intrari!$C$10/100) | L3: =IF(OR(H3="",I3="",J3="",K3="",D3=""),"",H3+I3+J3+K3+D3) | M3: =IF(OR(F3="",Intrari!$C$8=""),"",F3*(1-Intrari!$C$8/100)-IF(Intrari!$C$9="",0,Intrari!$C$9)) | N3: =IF(OR(L3="",M3=""),"",M3-L3) | O3: =IF(OR(N3="",B3="",B3=0),"",N3/B3) | P3: =IF(OR(N3="",M3="",M3=0),"",N3/M3)
A4: Litofanie plată sau cub cu LED | G4: Etsy: cuburi cu LED aprox. 15-60 USD (fără transport/taxe) | H4: =IF(OR(C4="",Intrari!$C$5=""),"",C4/1000*Intrari!$C$5) | I4: =IF(OR(B4="",Intrari!$C$6=""),"",B4*Intrari!$C$6) | J4: =IF(OR(E4="",Intrari!$C$7=""),"",E4/60*Intrari!$C$7) | K4: =IF(OR(H4="",I4="",Intrari!$C$10=""),"",(H4+I4)*Intrari!$C$10/100) | L4: =IF(OR(H4="",I4="",J4="",K4="",D4=""),"",H4+I4+J4+K4+D4) | M4: =IF(OR(F4="",Intrari!$C$8=""),"",F4*(1-Intrari!$C$8/100)-IF(Intrari!$C$9="",0,Intrari!$C$9)) | N4: =IF(OR(L4="",M4=""),"",M4-L4) | O4: =IF(OR(N4="",B4="",B4=0),"",N4/B4) | P4: =IF(OR(N4="",M4="",M4=0),"",N4/M4)
A5: Ghiveci / vază în formele LUMIS | G5: Etsy: 41% din anunțuri 10-25 USD, 31% 25-50 USD (estimare unui tool terț) | H5: =IF(OR(C5="",Intrari!$C$5=""),"",C5/1000*Intrari!$C$5) | I5: =IF(OR(B5="",Intrari!$C$6=""),"",B5*Intrari!$C$6) | J5: =IF(OR(E5="",Intrari!$C$7=""),"",E5/60*Intrari!$C$7) | K5: =IF(OR(H5="",I5="",Intrari!$C$10=""),"",(H5+I5)*Intrari!$C$10/100) | L5: =IF(OR(H5="",I5="",J5="",K5="",D5=""),"",H5+I5+J5+K5+D5) | M5: =IF(OR(F5="",Intrari!$C$8=""),"",F5*(1-Intrari!$C$8/100)-IF(Intrari!$C$9="",0,Intrari!$C$9)) | N5: =IF(OR(L5="",M5=""),"",M5-L5) | O5: =IF(OR(N5="",B5="",B5=0),"",N5/B5) | P5: =IF(OR(N5="",M5="",M5=0),"",N5/M5)
A6: Plăcuță / breloc cu nume | G6: Fără sursă | H6: =IF(OR(C6="",Intrari!$C$5=""),"",C6/1000*Intrari!$C$5) | I6: =IF(OR(B6="",Intrari!$C$6=""),"",B6*Intrari!$C$6) | J6: =IF(OR(E6="",Intrari!$C$7=""),"",E6/60*Intrari!$C$7) | K6: =IF(OR(H6="",I6="",Intrari!$C$10=""),"",(H6+I6)*Intrari!$C$10/100) | L6: =IF(OR(H6="",I6="",J6="",K6="",D6=""),"",H6+I6+J6+K6+D6) | M6: =IF(OR(F6="",Intrari!$C$8=""),"",F6*(1-Intrari!$C$8/100)-IF(Intrari!$C$9="",0,Intrari!$C$9)) | N6: =IF(OR(L6="",M6=""),"",M6-L6) | O6: =IF(OR(N6="",B6="",B6=0),"",N6/B6) | P6: =IF(OR(N6="",M6="",M6=0),"",N6/M6)
A7: Organizator de birou | G7: Fără sursă | H7: =IF(OR(C7="",Intrari!$C$5=""),"",C7/1000*Intrari!$C$5) | I7: =IF(OR(B7="",Intrari!$C$6=""),"",B7*Intrari!$C$6) | J7: =IF(OR(E7="",Intrari!$C$7=""),"",E7/60*Intrari!$C$7) | K7: =IF(OR(H7="",I7="",Intrari!$C$10=""),"",(H7+I7)*Intrari!$C$10/100) | L7: =IF(OR(H7="",I7="",J7="",K7="",D7=""),"",H7+I7+J7+K7+D7) | M7: =IF(OR(F7="",Intrari!$C$8=""),"",F7*(1-Intrari!$C$8/100)-IF(Intrari!$C$9="",0,Intrari!$C$9)) | N7: =IF(OR(L7="",M7=""),"",M7-L7) | O7: =IF(OR(N7="",B7="",B7=0),"",N7/B7) | P7: =IF(OR(N7="",M7="",M7=0),"",N7/M7)
A8: Piesă la comandă pentru o firmă | G8: Servicii RO (Brig.ro, rezumat de căutare): aprox. 0,50-0,60 lei/g + 10 lei/oră | H8: =IF(OR(C8="",Intrari!$C$5=""),"",C8/1000*Intrari!$C$5) | I8: =IF(OR(B8="",Intrari!$C$6=""),"",B8*Intrari!$C$6) | J8: =IF(OR(E8="",Intrari!$C$7=""),"",E8/60*Intrari!$C$7) | K8: =IF(OR(H8="",I8="",Intrari!$C$10=""),"",(H8+I8)*Intrari!$C$10/100) | L8: =IF(OR(H8="",I8="",J8="",K8="",D8=""),"",H8+I8+J8+K8+D8) | M8: =IF(OR(F8="",Intrari!$C$8=""),"",F8*(1-Intrari!$C$8/100)-IF(Intrari!$C$9="",0,Intrari!$C$9)) | N8: =IF(OR(L8="",M8=""),"",M8-L8) | O8: =IF(OR(N8="",B8="",B8=0),"",N8/B8) | P8: =IF(OR(N8="",M8="",M8=0),"",N8/M8)
A10: Cum se citește: ordonează produsele după „Profit / oră de imprimantă”. O marjă mare pe un print de 10 ore poate aduce mai puțin pe săptămână decât o marjă mică pe un print de 30 de minute.
A11: Costul rebuturilor se aplică la (material + mașină); transportul se scade o dată din venit. Mărimile nu au valori implicite: fără măsurători, celulele rămân goale.

Sheet Surse si limite
A1: Cercetare de piață: LUMIS/docs/cercetare-piata-2026-10-27.md (surse, date, limite).
A2: Fără date de vânzări pentru România. Reperele de preț sunt internaționale (USD), din anunțuri, fără transport și taxe.
A3: Prețul filamentului și costul mașinii: de completat din facturi. Nu există valori în cercetare care să se aplice în România.
A4: Lista lipsă: ore și grame măsurate din printuri reale; costul componentelor (LED, cablu, șuruburi, alice); preț ales; formă juridică și TVA; comisioane actuale; rată de rebuturi.
A5: Nu e o recomandare de preț și nu pornește nicio campanie sau cheltuială.
